gdacs/__init__.py
gdacs/api.py
gdacs/schemas.py
gdacs/utils.py
gdacs_api-2.0.0.dist-info/LICENSE
gdacs_api-2.0.0.dist-info/METADATA
gdacs_api-2.0.0.dist-info/WHEEL
gdacs_api-2.0.0.dist-info/top_level.txt
gdacs_api-2.0.0.dist-info/RECORD
