Metadata-Version: 2.1
Name: gdacs-api
Version: 2.0.0
Summary: Unofficial python library for working with GDACS API.
Home-page: https://github.com/Kamparia/gdacs-api
Author: Olaoye Anthony Somide
Author-email: olaoye.somide@wfp.org
License: MIT
Keywords: gdacs disasters earthquakes tropical-cyclones earthquakes floods
Classifier: Development Status :: 3 - Alpha
Classifier: Intended Audience :: Developers
Classifier: Operating System :: OS Independent
Classifier: License :: OSI Approved :: MIT License
Classifier: Programming Language :: Python :: 3
Classifier: Programming Language :: Python :: 3.6
Classifier: Programming Language :: Python :: 3.7
Classifier: Programming Language :: Python :: 3.8
Classifier: Programming Language :: Python :: 3.9
Classifier: Programming Language :: Python :: 3.10
Requires-Python: >=3.6
License-File: LICENSE
Requires-Dist: requests (>=2.10.0)
Requires-Dist: xmltodict
Requires-Dist: cachetools
Requires-Dist: pydantic
